{"type":"FeatureCollection", "features":[
{"type":"Feature","geometry":{"type":"Point","coordinates":[28.888876993000054,-2.443815051999934]},"properties":{"objectid":708,"layer":"Health post","district":"RUSIZI","name":"GIHAYA","type":"Health post","sector":"GIHUNDWE","cell":"GIHAYA","village":"KINYAGA","lat":-2.443815,"long":28.888877,"comments":"FUNCTIONAL","source":"Ministry of Health","capture":"2016","globalid":"{37C4E6E7-F727-4DC0-9F92-D65B587855E0}","created_us":null,"created_da":null,"last_edite":null,"last_edi_1":null}},
{"type":"Feature","geometry":{"type":"Point","coordinates":[28.908599994000042,-2.448996051999927]},"properties":{"objectid":870,"layer":"Health post","district":"RUSIZI","name":"MUHARI","type":"Health post","sector":"GIHUNDWE","cell":"KAMATITA","village":"MUHARI","lat":-2.448996,"long":28.9086,"comments":"FUNCTIONAL","source":"Ministry of Health","capture":"2016","globalid":"{E845DC99-6C79-4305-89DB-1CA502B66D7C}","created_us":null,"created_da":null,"last_edite":null,"last_edi_1":null}},
{"type":"Feature","geometry":{"type":"Point","coordinates":[28.949579993000043,-2.497489051999935]},"properties":{"objectid":1049,"layer":"Health post","district":"RUSIZI","name":"RYAMUHIRWA","type":"Health post","sector":"NKUNGU","cell":"RYAMUHIRWA","village":"NYARUSHISHI","lat":-2.497489,"long":28.94958,"comments":"FUTURE HEALTH POST-SITE IDENTIFIED-UNDER CONSTRUCTION","source":"Ministry of Health","capture":"2016","globalid":"{6091FE2F-C083-4E04-9B6E-913850BAEA9F}","created_us":null,"created_da":null,"last_edite":null,"last_edi_1":null}}
]}
